ballet/__init__.py
ballet/cli.py
ballet/client.py
ballet/compat.py
ballet/contrib.py
ballet/discovery.py
ballet/encoder.py
ballet/exc.py
ballet/feature.py
ballet/pipeline.py
ballet/project.py
ballet/templating.py
ballet/transformer.py
ballet/update.py
ballet/eng/__init__.py
ballet/eng/base.py
ballet/eng/misc.py
ballet/eng/missing.py
ballet/eng/ts.py
ballet/eng/external/__init__.py
ballet/eng/external/category_encoders.py
ballet/eng/external/feature_engine.py
ballet/eng/external/featuretools.py
ballet/eng/external/skits.py
ballet/eng/external/sklearn.py
ballet/eng/external/tsfresh.py
ballet/mlprimitives/__init__.py
ballet/mlprimitives/pipelines/ballet_rf_classifier.json
ballet/mlprimitives/pipelines/ballet_rf_regressor.json
ballet/mlprimitives/primitives/ballet.drop_missing_targets.json
ballet/mlprimitives/primitives/ballet.encode_target.json
ballet/mlprimitives/primitives/ballet.engineer_features.json
ballet/templates/feature_template/cookiecutter.json
ballet/templates/feature_template/{{ cookiecutter._dir }}/__init__.py
ballet/templates/feature_template/{{ cookiecutter._dir }}/user_{{ cookiecutter.username }}/__init__.py
ballet/templates/feature_template/{{ cookiecutter._dir }}/user_{{ cookiecutter.username }}/feature_{{ cookiecutter.featurename }}.py
ballet/templates/project_template/cookiecutter.json
ballet/templates/project_template/hooks/post_gen_project.py
ballet/templates/project_template/{{cookiecutter.project_slug}}/.cookiecutter_context.json
ballet/templates/project_template/{{cookiecutter.project_slug}}/.gitignore
ballet/templates/project_template/{{cookiecutter.project_slug}}/.travis.yml
ballet/templates/project_template/{{cookiecutter.project_slug}}/README.md
ballet/templates/project_template/{{cookiecutter.project_slug}}/ballet.yml
ballet/templates/project_template/{{cookiecutter.project_slug}}/requirements-notebook.txt
ballet/templates/project_template/{{cookiecutter.project_slug}}/requirements.txt
ballet-0.19.5.dist-info/AUTHORS.rst
ballet-0.19.5.dist-info/LICENSE
ballet-0.19.5.dist-info/METADATA
ballet-0.19.5.dist-info/WHEEL
ballet-0.19.5.dist-info/entry_points.txt
ballet-0.19.5.dist-info/top_level.txt
ballet-0.19.5.dist-info/RECORD
