Metadata-Version: 2.1
Name: ballet
Version: 0.19.5
Summary: Core functionality for lightweight, collaborative data science projects
Home-page: https://github.com/ballet/ballet
Author: Micah Smith
Author-email: micahs@mit.edu
License: MIT license
Keywords: ballet
Platform: UNKNOWN
Classifier: Development Status :: 2 - Pre-Alpha
Classifier: Intended Audience :: Developers
Classifier: License :: OSI Approved :: MIT License
Classifier: Natural Language :: English
Classifier: Programming Language :: Python :: 3
Classifier: Programming Language :: Python :: 3.6
Classifier: Programming Language :: Python :: 3.7
Classifier: Programming Language :: Python :: 3.8
Requires-Python: >=3.6.1
Requires-Dist: black
Requires-Dist: cookiecutter
Requires-Dist: Click (>=6.0)
Requires-Dist: dill
Requires-Dist: dynaconf (~=3.0)
Requires-Dist: funcy (>=1.14)
Requires-Dist: gitpython
Requires-Dist: h5py
Requires-Dist: numpy
Requires-Dist: packaging
Requires-Dist: pandas (~=1.0)
Requires-Dist: pygithub (~=1.54)
Requires-Dist: python-slugify (~=4.0)
Requires-Dist: pyyaml
Requires-Dist: requests
Requires-Dist: scipy
Requires-Dist: sklearn-pandas (~=1.0)
Requires-Dist: stacklog
Requires-Dist: tqdm
Requires-Dist: dataclasses ; python_version == "3.6"
Requires-Dist: scikit-learn (<0.23,>=0.20) ; python_version == "3.6"
Requires-Dist: scikit-learn (>=0.20) ; python_version > "3.6"
Provides-Extra: all
Requires-Dist: category-encoders (>=2.2.2) ; extra == 'all'
Requires-Dist: feature-engine (~=1.0) ; extra == 'all'
Requires-Dist: featuretools-sklearn-transformer (>=0.1) ; extra == 'all'
Requires-Dist: skits (>=0.1.2) ; extra == 'all'
Requires-Dist: tsfresh (>=0.16) ; extra == 'all'
Provides-Extra: category_encoders
Requires-Dist: category-encoders (>=2.2.2) ; extra == 'category_encoders'
Provides-Extra: dev
Requires-Dist: types-pkg-resources ; extra == 'dev'
Requires-Dist: types-requests ; extra == 'dev'
Requires-Dist: types-python-slugify ; extra == 'dev'
Requires-Dist: bump2version (>=1) ; extra == 'dev'
Requires-Dist: pip (>=9.0.1) ; extra == 'dev'
Requires-Dist: watchdog[watchmedo] (>=0.8.3) ; extra == 'dev'
Requires-Dist: invoke (>=1.4) ; extra == 'dev'
Requires-Dist: mypy (>=0.812) ; extra == 'dev'
Requires-Dist: m2r2 (>=0.2.5) ; extra == 'dev'
Requires-Dist: sphinx (~=3.0) ; extra == 'dev'
Requires-Dist: sphinx-rtd-theme (>=0.2.4) ; extra == 'dev'
Requires-Dist: sphinx-click (>=2.2) ; extra == 'dev'
Requires-Dist: sphinx-autodoc-typehints (>=1.11) ; extra == 'dev'
Requires-Dist: sphinx-copybutton (>=0.3.1) ; extra == 'dev'
Requires-Dist: rstcheck ; extra == 'dev'
Requires-Dist: flake8 (>=3.5.0) ; extra == 'dev'
Requires-Dist: isort (>=5.0) ; extra == 'dev'
Requires-Dist: autopep8 (>=1.3.5) ; extra == 'dev'
Requires-Dist: twine (>=1.10.0) ; extra == 'dev'
Requires-Dist: wheel (>=0.30.0) ; extra == 'dev'
Requires-Dist: coverage (>=4.5.1) ; extra == 'dev'
Requires-Dist: pytest (>=6) ; extra == 'dev'
Requires-Dist: pytest-cov (>=2.6) ; extra == 'dev'
Requires-Dist: pytest-virtualenv (>=1.7.0) ; extra == 'dev'
Requires-Dist: tox (>=2.9.1) ; extra == 'dev'
Requires-Dist: responses (>=0.13.2) ; extra == 'dev'
Provides-Extra: feature_engine
Requires-Dist: feature-engine (~=1.0) ; extra == 'feature_engine'
Provides-Extra: featuretools
Requires-Dist: featuretools-sklearn-transformer (>=0.1) ; extra == 'featuretools'
Provides-Extra: skits
Requires-Dist: skits (>=0.1.2) ; extra == 'skits'
Provides-Extra: test
Requires-Dist: coverage (>=4.5.1) ; extra == 'test'
Requires-Dist: pytest (>=6) ; extra == 'test'
Requires-Dist: pytest-cov (>=2.6) ; extra == 'test'
Requires-Dist: pytest-virtualenv (>=1.7.0) ; extra == 'test'
Requires-Dist: tox (>=2.9.1) ; extra == 'test'
Requires-Dist: responses (>=0.13.2) ; extra == 'test'
Provides-Extra: tsfresh
Requires-Dist: tsfresh (>=0.16) ; extra == 'tsfresh'
